{
  "info": {
    "name": "ClarityHub Backend API",
    "description": "Complete API collection for ClarityHub Backend with authentication and user management endpoints",
    "version": "1.0.0",
    "schema": "https://schema.getpostman.com/json/collection/v2.1.0/collection.json"
  },
  "auth": {
    "type": "bearer",
    "bearer": [
      {
        "key": "token",
        "value": "{{jwt_token}}",
        "type": "string"
      }
    ]
  },
  "event": [
    {
      "listen": "prerequest",
      "script": {
        "type": "text/javascript",
        "exec": [
          ""
        ]
      }
    },
    {
      "listen": "test",
      "script": {
        "type": "text/javascript",
        "exec": [
          ""
        ]
      }
    }
  ],
  "variable": [
    {
      "key": "base_url",
      "value": "http://localhost:3000",
      "type": "string"
    },
    {
      "key": "jwt_token",
      "value": "",
      "type": "string"
    },
    {
      "key": "user_id",
      "value": "",
      "type": "string"
    },
    {
      "key": "admin_token",
      "value": "",
      "type": "string"
    }
  ],
  "item": [
    {
      "name": "Health Check",
      "item": [
        {
          "name": "Health Check",
          "event": [
            {
              "listen": "test",
              "script": {
                "exec": [
                  "pm.test('Status code is 200', function () {",
                  "    pm.response.to.have.status(200);",
                  "});",
                  "",
                  "pm.test('Response has correct structure', function () {",
                  "    const responseJson = pm.response.json();",
                  "    pm.expect(responseJson).to.have.property('status', 'OK');",
                  "    pm.expect(responseJson).to.have.property('message', 'ClarityHub Backend is running');",
                  "    pm.expect(responseJson).to.have.property('timestamp');",
                  "});"
                ],
                "type": "text/javascript"
              }
            }
          ],
          "request": {
            "method": "GET",
            "header": [],
            "url": {
              "raw": "{{base_url}}/health",
              "host": [
                "{{base_url}}"
              ],
              "path": [
                "health"
              ]
            }
          },
          "response": []
        }
      ]
    },
    {
      "name": "Authentication",
      "item": [
        {
          "name": "User Signup",
          "event": [
            {
              "listen": "test",
              "script": {
                "exec": [
                  "pm.test('Status code is 201', function () {",
                  "    pm.response.to.have.status(201);",
                  "});",
                  "",
                  "pm.test('Response has token and user data', function () {",
                  "    const responseJson = pm.response.json();",
                  "    pm.expect(responseJson).to.have.property('token');",
                  "    pm.expect(responseJson).to.have.property('user');",
                  "    pm.expect(responseJson.user).to.have.property('id');",
                  "    pm.expect(responseJson.user).to.have.property('email');",
                  "    ",
                  "    // Save token and user ID for other requests",
                  "    pm.collectionVariables.set('jwt_token', responseJson.token);",
                  "    pm.collectionVariables.set('user_id', responseJson.user.id);",
                  "});"
                ],
                "type": "text/javascript"
              }
            }
          ],
          "request": {
            "method": "POST",
            "header": [
              {
                "key": "Content-Type",
                "value": "application/json"
              }
            ],
            "body": {
              "mode": "raw",
              "raw": "{\n  \"name\": \"John Doe\",\n  \"email\": \"john.doe@example.com\",\n  \"password\": \"securepassword123\"\n}"
            },
            "url": {
              "raw": "{{base_url}}/api/auth/signup",
              "host": [
                "{{base_url}}"
              ],
              "path": [
                "api",
                "auth",
                "signup"
              ]
            }
          },
          "response": []
        },
        {
          "name": "User Login",
          "event": [
            {
              "listen": "test",
              "script": {
                "exec": [
                  "pm.test('Status code is 200', function () {",
                  "    pm.response.to.have.status(200);",
                  "});",
                  "",
                  "pm.test('Login successful with token', function () {",
                  "    const responseJson = pm.response.json();",
                  "    pm.expect(responseJson).to.have.property('token');",
                  "    pm.expect(responseJson).to.have.property('user');",
                  "    pm.expect(responseJson.message).to.equal('Login successful');",
                  "    ",
                  "    // Update token for authenticated requests",
                  "    pm.collectionVariables.set('jwt_token', responseJson.token);",
                  "});"
                ],
                "type": "text/javascript"
              }
            }
          ],
          "request": {
            "method": "POST",
            "header": [
              {
                "key": "Content-Type",
                "value": "application/json"
              }
            ],
            "body": {
              "mode": "raw",
              "raw": "{\n  \"email\": \"john.doe@example.com\",\n  \"password\": \"securepassword123\"\n}"
            },
            "url": {
              "raw": "{{base_url}}/api/auth/login",
              "host": [
                "{{base_url}}"
              ],
              "path": [
                "api",
                "auth",
                "login"
              ]
            }
          },
          "response": []
        },
        {
          "name": "Get Profile",
          "event": [
            {
              "listen": "test",
              "script": {
                "exec": [
                  "pm.test('Status code is 200', function () {",
                  "    pm.response.to.have.status(200);",
                  "});",
                  "",
                  "pm.test('Profile data is returned', function () {",
                  "    const responseJson = pm.response.json();",
                  "    pm.expect(responseJson).to.have.property('user');",
                  "    pm.expect(responseJson.user).to.have.property('id');",
                  "    pm.expect(responseJson.user).to.have.property('name');",
                  "    pm.expect(responseJson.user).to.have.property('email');",
                  "});"
                ],
                "type": "text/javascript"
              }
            }
          ],
          "request": {
            "method": "GET",
            "header": [
              {
                "key": "Authorization",
                "value": "Bearer {{jwt_token}}"
              }
            ],
            "url": {
              "raw": "{{base_url}}/api/auth/profile",
              "host": [
                "{{base_url}}"
              ],
              "path": [
                "api",
                "auth",
                "profile"
              ]
            }
          },
          "response": []
        },
        {
          "name": "Update Profile",
          "event": [
            {
              "listen": "test",
              "script": {
                "exec": [
                  "pm.test('Status code is 200', function () {",
                  "    pm.response.to.have.status(200);",
                  "});",
                  "",
                  "pm.test('Profile updated successfully', function () {",
                  "    const responseJson = pm.response.json();",
                  "    pm.expect(responseJson).to.have.property('message', 'Profile updated successfully');",
                  "    pm.expect(responseJson).to.have.property('user');",
                  "});"
                ],
                "type": "text/javascript"
              }
            }
          ],
          "request": {
            "method": "PUT",
            "header": [
              {
                "key": "Authorization",
                "value": "Bearer {{jwt_token}}"
              },
              {
                "key": "Content-Type",
                "value": "application/json"
              }
            ],
            "body": {
              "mode": "raw",
              "raw": "{\n  \"name\": \"John Doe Updated\",\n  \"email\": \"john.doe.updated@example.com\"\n}"
            },
            "url": {
              "raw": "{{base_url}}/api/auth/profile",
              "host": [
                "{{base_url}}"
              ],
              "path": [
                "api",
                "auth",
                "profile"
              ]
            }
          },
          "response": []
        }
      ]
    },
    {
      "name": "Admin Operations",
      "item": [
        {
          "name": "Create Admin User",
          "event": [
            {
              "listen": "test",
              "script": {
                "exec": [
                  "pm.test('Admin user created successfully', function () {",
                  "    pm.response.to.have.status(201);",
                  "    const responseJson = pm.response.json();",
                  "    pm.expect(responseJson).to.have.property('token');",
                  "    ",
                  "    // Save admin token for admin operations",
                  "    pm.collectionVariables.set('admin_token', responseJson.token);",
                  "});"
                ],
                "type": "text/javascript"
              }
            }
          ],
          "request": {
            "method": "POST",
            "header": [
              {
                "key": "Content-Type",
                "value": "application/json"
              }
            ],
            "body": {
              "mode": "raw",
              "raw": "{\n  \"name\": \"Admin User\",\n  \"email\": \"admin@clarityhub.com\",\n  \"password\": \"adminpassword123\"\n}"
            },
            "url": {
              "raw": "{{base_url}}/api/auth/signup",
              "host": [
                "{{base_url}}"
              ],
              "path": [
                "api",
                "auth",
                "signup"
              ]
            }
          },
          "response": []
        }
      ]
    },
    {
      "name": "User Management",
      "item": [
        {
          "name": "Get All Users (Admin)",
          "event": [
            {
              "listen": "test",
              "script": {
                "exec": [
                  "pm.test('Status code is 200', function () {",
                  "    pm.response.to.have.status(200);",
                  "});",
                  "",
                  "pm.test('Users list returned with pagination', function () {",
                  "    const responseJson = pm.response.json();",
                  "    pm.expect(responseJson).to.have.property('users');",
                  "    pm.expect(responseJson).to.have.property('pagination');",
                  "    pm.expect(responseJson.users).to.be.an('array');",
                  "});"
                ],
                "type": "text/javascript"
              }
            }
          ],
          "request": {
            "method": "GET",
            "header": [
              {
                "key": "Authorization",
                "value": "Bearer {{admin_token}}"
              }
            ],
            "url": {
              "raw": "{{base_url}}/api/users?page=1&limit=10",
              "host": [
                "{{base_url}}"
              ],
              "path": [
                "api",
                "users"
              ],
              "query": [
                {
                  "key": "page",
                  "value": "1"
                },
                {
                  "key": "limit",
                  "value": "10"
                }
              ]
            }
          },
          "response": []
        },
        {
          "name": "Get User by ID",
          "event": [
            {
              "listen": "test",
              "script": {
                "exec": [
                  "pm.test('Status code is 200', function () {",
                  "    pm.response.to.have.status(200);",
                  "});",
                  "",
                  "pm.test('User data returned', function () {",
                  "    const responseJson = pm.response.json();",
                  "    pm.expect(responseJson).to.have.property('user');",
                  "    pm.expect(responseJson.user).to.have.property('id');",
                  "});"
                ],
                "type": "text/javascript"
              }
            }
          ],
          "request": {
            "method": "GET",
            "header": [
              {
                "key": "Authorization",
                "value": "Bearer {{jwt_token}}"
              }
            ],
            "url": {
              "raw": "{{base_url}}/api/users/{{user_id}}",
              "host": [
                "{{base_url}}"
              ],
              "path": [
                "api",
                "users",
                "{{user_id}}"
              ]
            }
          },
          "response": []
        },
        {
          "name": "Update User (Admin)",
          "event": [
            {
              "listen": "test",
              "script": {
                "exec": [
                  "pm.test('Status code is 200', function () {",
                  "    pm.response.to.have.status(200);",
                  "});",
                  "",
                  "pm.test('User updated successfully', function () {",
                  "    const responseJson = pm.response.json();",
                  "    pm.expect(responseJson).to.have.property('message', 'User updated successfully');",
                  "});"
                ],
                "type": "text/javascript"
              }
            }
          ],
          "request": {
            "method": "PUT",
            "header": [
              {
                "key": "Authorization",
                "value": "Bearer {{admin_token}}"
              },
              {
                "key": "Content-Type",
                "value": "application/json"
              }
            ],
            "body": {
              "mode": "raw",
              "raw": "{\n  \"name\": \"Updated User Name\",\n  \"role\": \"admin\",\n  \"isActive\": true\n}"
            },
            "url": {
              "raw": "{{base_url}}/api/users/{{user_id}}",
              "host": [
                "{{base_url}}"
              ],
              "path": [
                "api",
                "users",
                "{{user_id}}"
              ]
            }
          },
          "response": []
        },
        {
          "name": "Delete User (Admin)",
          "event": [
            {
              "listen": "test",
              "script": {
                "exec": [
                  "pm.test('Status code is 200', function () {",
                  "    pm.response.to.have.status(200);",
                  "});",
                  "",
                  "pm.test('User deleted successfully', function () {",
                  "    const responseJson = pm.response.json();",
                  "    pm.expect(responseJson).to.have.property('message', 'User deleted successfully');",
                  "});"
                ],
                "type": "text/javascript"
              }
            }
          ],
          "request": {
            "method": "DELETE",
            "header": [
              {
                "key": "Authorization",
                "value": "Bearer {{admin_token}}"
              }
            ],
            "url": {
              "raw": "{{base_url}}/api/users/{{user_id}}",
              "host": [
                "{{base_url}}"
              ],
              "path": [
                "api",
                "users",
                "{{user_id}}"
              ]
            }
          },
          "response": []
        }
      ]
    },
    {
      "name": "Error Scenarios",
      "item": [
        {
          "name": "Invalid Login",
          "event": [
            {
              "listen": "test",
              "script": {
                "exec": [
                  "pm.test('Status code is 401', function () {",
                  "    pm.response.to.have.status(401);",
                  "});",
                  "",
                  "pm.test('Error message returned', function () {",
                  "    const responseJson = pm.response.json();",
                  "    pm.expect(responseJson).to.have.property('error');",
                  "});"
                ],
                "type": "text/javascript"
              }
            }
          ],
          "request": {
            "method": "POST",
            "header": [
              {
                "key": "Content-Type",
                "value": "application/json"
              }
            ],
            "body": {
              "mode": "raw",
              "raw": "{\n  \"email\": \"nonexistent@example.com\",\n  \"password\": \"wrongpassword\"\n}"
            },
            "url": {
              "raw": "{{base_url}}/api/auth/login",
              "host": [
                "{{base_url}}"
              ],
              "path": [
                "api",
                "auth",
                "login"
              ]
            }
          },
          "response": []
        },
        {
          "name": "Unauthorized Access",
          "event": [
            {
              "listen": "test",
              "script": {
                "exec": [
                  "pm.test('Status code is 401', function () {",
                  "    pm.response.to.have.status(401);",
                  "});",
                  "",
                  "pm.test('Unauthorized error returned', function () {",
                  "    const responseJson = pm.response.json();",
                  "    pm.expect(responseJson).to.have.property('error');",
                  "});"
                ],
                "type": "text/javascript"
              }
            }
          ],
          "request": {
            "method": "GET",
            "header": [],
            "url": {
              "raw": "{{base_url}}/api/auth/profile",
              "host": [
                "{{base_url}}"
              ],
              "path": [
                "api",
                "auth",
                "profile"
              ]
            }
          },
          "response": []
        },
        {
          "name": "Validation Error",
          "event": [
            {
              "listen": "test",
              "script": {
                "exec": [
                  "pm.test('Status code is 400', function () {",
                  "    pm.response.to.have.status(400);",
                  "});",
                  "",
                  "pm.test('Validation error returned', function () {",
                  "    const responseJson = pm.response.json();",
                  "    pm.expect(responseJson).to.have.property('error');",
                  "    pm.expect(responseJson).to.have.property('details');",
                  "});"
                ],
                "type": "text/javascript"
              }
            }
          ],
          "request": {
            "method": "POST",
            "header": [
              {
                "key": "Content-Type",
                "value": "application/json"
              }
            ],
            "body": {
              "mode": "raw",
              "raw": "{\n  \"name\": \"\",\n  \"email\": \"invalid-email\",\n  \"password\": \"123\"\n}"
            },
            "url": {
              "raw": "{{base_url}}/api/auth/signup",
              "host": [
                "{{base_url}}"
              ],
              "path": [
                "api",
                "auth",
                "signup"
              ]
            }
          },
          "response": []
        },
        {
          "name": "Route Not Found",
          "event": [
            {
              "listen": "test",
              "script": {
                "exec": [
                  "pm.test('Status code is 404', function () {",
                  "    pm.response.to.have.status(404);",
                  "});",
                  "",
                  "pm.test('Not found error returned', function () {",
                  "    const responseJson = pm.response.json();",
                  "    pm.expect(responseJson).to.have.property('error', 'Route not found');",
                  "});"
                ],
                "type": "text/javascript"
              }
            }
          ],
          "request": {
            "method": "GET",
            "header": [],
            "url": {
              "raw": "{{base_url}}/api/nonexistent",
              "host": [
                "{{base_url}}"
              ],
              "path": [
                "api",
                "nonexistent"
              ]
            }
          },
          "response": []
        }
      ]
    }
  ]
}